PQEnalyzer/__init__.py
PQEnalyzer/__main__.py
PQEnalyzer/__version__.py
PQEnalyzer/apps/__init__.py
PQEnalyzer/apps/app.py
PQEnalyzer/apps/termapp.py
PQEnalyzer/icons/icon.png
PQEnalyzer/plots/__init__.py
PQEnalyzer/plots/plot.py
PQEnalyzer/plots/plot_histogram.py
PQEnalyzer/plots/plot_time.py
PQEnalyzer/plots/termplot.py
PQEnalyzer/readers/__init__.py
PQEnalyzer/readers/reader.py
PQEnalyzer/statistics/__init__.py
PQEnalyzer/statistics/statistic.py
PQEnalyzer-0.7.0.dist-info/LICENSE
PQEnalyzer-0.7.0.dist-info/METADATA
PQEnalyzer-0.7.0.dist-info/WHEEL
PQEnalyzer-0.7.0.dist-info/entry_points.txt
PQEnalyzer-0.7.0.dist-info/top_level.txt
PQEnalyzer-0.7.0.dist-info/RECORD
